{
  "streams": [
    {
      "title": "a new stream with user id",
      "description": "should have user id in this stream object",
      "userId": "108801403594781455386",
      "id": 4
    },
    {
      "title": "my second test",
      "description": "test description with user id",
      "userId": "108801403594781455386",
      "id": 5
    },
    {
      "title": "refactored form test",
      "description": "test test test",
      "id": 9
    },
    {
      "title": "test 3",
      "description": "test 3 test",
      "id": 10
    }
  ]
}